discord/ext/class_commands/__init__.py
discord/ext/class_commands/commands.py
discord/ext/class_commands/interop.py
discord/ext/class_commands/option.py
discord/ext/class_commands/py.typed
discord_class_commands-1.1.0.dist-info/LICENSE
discord_class_commands-1.1.0.dist-info/METADATA
discord_class_commands-1.1.0.dist-info/WHEEL
discord_class_commands-1.1.0.dist-info/top_level.txt
discord_class_commands-1.1.0.dist-info/RECORD
