Metadata-Version: 2.1
Name: discord-class-commands
Version: 1.1.0
Summary: A discord.py extension module to facilitate class-based creation of application commands.
Home-page: https://github.com/dolfies/discord-class-commands
Author: Dolfies
License: MIT
Project-URL: Documentation, https://example.com/
Project-URL: Issue tracker, https://github.com/dolfies/discord-class-commands/issues
Platform: UNKNOWN
Classifier: License :: OSI Approved :: MIT License
Classifier: Intended Audience :: Developers
Classifier: Natural Language :: English
Classifier: Operating System :: OS Independent
Classifier: Programming Language :: Python :: 3.8
Classifier: Programming Language :: Python :: 3.9
Classifier: Programming Language :: Python :: 3.10
Classifier: Topic :: Internet
Classifier: Topic :: Software Development :: Libraries
Classifier: Topic :: Software Development :: Libraries :: Python Modules
Classifier: Topic :: Utilities
Classifier: Typing :: Typed
Requires-Python: >=3.8.0
License-File: LICENSE
Provides-Extra: docs
Requires-Dist: sphinx (==4.4.0) ; extra == 'docs'
Requires-Dist: sphinxcontrib-trio (==1.1.2) ; extra == 'docs'
Requires-Dist: sphinxcontrib-websupport ; extra == 'docs'
Requires-Dist: typing-extensions ; extra == 'docs'
